obswebsocket/__init__.py
obswebsocket/base_classes.py
obswebsocket/core.py
obswebsocket/events.py
obswebsocket/exceptions.py
obswebsocket/requests.py
obs_websocket_py-0.4.dist-info/LICENSE
obs_websocket_py-0.4.dist-info/METADATA
obs_websocket_py-0.4.dist-info/WHEEL
obs_websocket_py-0.4.dist-info/top_level.txt
obs_websocket_py-0.4.dist-info/RECORD
