Metadata-Version: 2.1
Name: obs-websocket-py
Version: 0.4
Summary: Python library to communicate with an obs-websocket server.
Home-page: https://github.com/Elektordi/obs-websocket-py
Author: Guillaume "Elektordi" Genty
Author-email: elektordi@elektordi.net
License: MIT
Download-URL: https://github.com/Elektordi/obs-websocket-py/archive/0.4.tar.gz
Keywords: obs,obs-studio,websocket
Platform: UNKNOWN
Classifier: License :: OSI Approved :: MIT License
Classifier: Environment :: Plugins
Classifier: Intended Audience :: Developers
Classifier: Topic :: Software Development :: Libraries
Classifier: Development Status :: 4 - Beta
Classifier: Programming Language :: Python :: 2
Classifier: Programming Language :: Python :: 2.7
Classifier: Programming Language :: Python :: 3
Classifier: Programming Language :: Python :: 3.5
Requires-Dist: websocket-client
